LICENSE.txt
MANIFEST.in
README.rst
setup.py
digicert_client/__init__.py
digicert_client.egg-info/PKG-INFO
digicert_client.egg-info/SOURCES.txt
digicert_client.egg-info/dependency_links.txt
digicert_client.egg-info/not-zip-safe
digicert_client.egg-info/top_level.txt
digicert_client/api/__init__.py
digicert_client/api/commands/__init__.py
digicert_client/api/commands/v1.py
digicert_client/api/commands/v2.py
digicert_client/api/queries/__init__.py
digicert_client/api/queries/v1.py
digicert_client/api/queries/v2.py
digicert_client/https/DigiCertRoots.pem
digicert_client/https/__init__.py