Metadata-Version: 1.1
Name: digicert-client
Version: 1.0.1
Summary: DigiCert, Inc. web API client library
Home-page: http://github.com/digicert/digicert_client/python
Author: DigiCert, Inc.
Author-email: support@digicert.com
License: MIT
Platform: UNKNOWN
Classifier: Development Status :: 5 - Production/Stable
Classifier: Intended Audience :: Information Technology
Classifier: License :: OSI Approved :: MIT License
Classifier: Programming Language :: Python :: 2.7
Classifier: Topic :: Security
